<?xml version="1.0" encoding="UTF-8"?>
<objects serializationModel="Studio.01.08.00">
    <object class="Event" id="{a2f5fd1e-d92a-4416-864c-f87af3e3c324}">
        <property name="name">
            <value>Music Box Hand</value>
        </property>
        <property name="note">
            <value>Sound of the music box &quot;impacting&quot; the players hand.</value>
        </property>
        <property name="outputFormat">
            <value>1</value>
        </property>
        <relationship name="mixer">
            <destination>{1e67d968-3126-45af-8587-cf9029990ada}</destination>
        </relationship>
        <relationship name="masterTrack">
            <destination>{fbf08079-b17d-4ca8-b819-780f2ee878b4}</destination>
        </relationship>
        <relationship name="mixerInput">
            <destination>{804d3f06-8cbe-4655-91d6-58cba0357c11}</destination>
        </relationship>
        <relationship name="automatableProperties">
            <destination>{bfa6cf1b-66a3-4a5c-94b9-40d4f9eb723a}</destination>
        </relationship>
        <relationship name="markerTracks">
            <destination>{79b2e229-30d2-4e04-b5ee-d3914f25255a}</destination>
        </relationship>
        <relationship name="groupTracks">
            <destination>{e5711bd7-dd4a-46da-ad92-0872ff5c1087}</destination>
        </relationship>
        <relationship name="timeline">
            <destination>{b357597e-72c0-4666-befc-bc95ad9cd9a7}</destination>
        </relationship>
        <relationship name="banks">
            <destination>{c2b19aa5-23d7-4bc3-81cc-7799979aef39}</destination>
        </relationship>
        <relationship name="folder">
            <destination>{730ae8dc-296b-4baf-b80e-ef36a95facd0}</destination>
        </relationship>
    </object>
    <object class="EventMixer" id="{1e67d968-3126-45af-8587-cf9029990ada}">
        <relationship name="masterBus">
            <destination>{c93dfd8a-6118-4aff-9488-e86b55289c37}</destination>
        </relationship>
    </object>
    <object class="MasterTrack" id="{fbf08079-b17d-4ca8-b819-780f2ee878b4}">
        <relationship name="mixerGroup">
            <destination>{c93dfd8a-6118-4aff-9488-e86b55289c37}</destination>
        </relationship>
    </object>
    <object class="MixerInput" id="{804d3f06-8cbe-4655-91d6-58cba0357c11}">
        <relationship name="effectChain">
            <destination>{7f1309c8-8d4f-4b04-b041-9ca916b812a6}</destination>
        </relationship>
        <relationship name="panner">
            <destination>{2d839713-5a52-43b0-ac1f-8b286a22ba24}</destination>
        </relationship>
        <relationship name="output">
            <destination>{7ba2ac69-fc91-4f4c-a1a9-79c8f95ccf3f}</destination>
        </relationship>
    </object>
    <object class="EventAutomatableProperties" id="{bfa6cf1b-66a3-4a5c-94b9-40d4f9eb723a}"/>
    <object class="MarkerTrack" id="{79b2e229-30d2-4e04-b5ee-d3914f25255a}"/>
    <object class="GroupTrack" id="{e5711bd7-dd4a-46da-ad92-0872ff5c1087}">
        <relationship name="modules">
            <destination>{bb54e11a-a17e-4916-9d13-83e1a2710ba3}</destination>
        </relationship>
        <relationship name="mixerGroup">
            <destination>{9c914341-417c-426c-8f8e-3bf1d61954ca}</destination>
        </relationship>
    </object>
    <object class="Timeline" id="{b357597e-72c0-4666-befc-bc95ad9cd9a7}">
        <relationship name="modules">
            <destination>{bb54e11a-a17e-4916-9d13-83e1a2710ba3}</destination>
        </relationship>
    </object>
    <object class="EventMixerMaster" id="{c93dfd8a-6118-4aff-9488-e86b55289c37}">
        <relationship name="effectChain">
            <destination>{07e6cc3d-cf26-425d-8b1f-2be7501e55e5}</destination>
        </relationship>
        <relationship name="panner">
            <destination>{983817c2-d96c-4f32-8936-7d456b5814f1}</destination>
        </relationship>
        <relationship name="mixer">
            <destination>{1e67d968-3126-45af-8587-cf9029990ada}</destination>
        </relationship>
    </object>
    <object class="MixerBusEffectChain" id="{7f1309c8-8d4f-4b04-b041-9ca916b812a6}">
        <relationship name="effects">
            <destination>{f76d13c8-9cc0-42a2-8a3f-f8d4110b069b}</destination>
        </relationship>
    </object>
    <object class="MixerBusPanner" id="{2d839713-5a52-43b0-ac1f-8b286a22ba24}"/>
    <object class="MultiSound" id="{bb54e11a-a17e-4916-9d13-83e1a2710ba3}">
        <property name="start">
            <value>0</value>
        </property>
        <property name="length">
            <value>2</value>
        </property>
        <property name="pitch">
            <value>-2</value>
        </property>
        <relationship name="sounds">
            <destination>{2261fe03-77a6-4d6e-ab79-865616aac57d}</destination>
            <destination>{ec0cc84a-3a05-45b9-98ce-1a0c967fb429}</destination>
            <destination>{7ca97bbe-23f8-4141-ba01-d0de388f328e}</destination>
        </relationship>
    </object>
    <object class="EventMixerGroup" id="{9c914341-417c-426c-8f8e-3bf1d61954ca}">
        <property name="volume">
            <value>-3</value>
        </property>
        <property name="name">
            <value>Audio 1</value>
        </property>
        <relationship name="effectChain">
            <destination>{5d252439-200f-461b-89f0-360635b470fb}</destination>
        </relationship>
        <relationship name="panner">
            <destination>{8d42dc06-b7f1-4c29-b059-fba4429723a2}</destination>
        </relationship>
        <relationship name="output">
            <destination>{c93dfd8a-6118-4aff-9488-e86b55289c37}</destination>
        </relationship>
    </object>
    <object class="MixerBusEffectChain" id="{07e6cc3d-cf26-425d-8b1f-2be7501e55e5}">
        <relationship name="effects">
            <destination>{4940ee67-826a-45df-8e5e-c160b2e86bd2}</destination>
            <destination>{b6a5cd0a-d96e-4ad8-a66a-9d5de803f746}</destination>
        </relationship>
    </object>
    <object class="MixerBusPanner" id="{983817c2-d96c-4f32-8936-7d456b5814f1}"/>
    <object class="MixerBusFader" id="{f76d13c8-9cc0-42a2-8a3f-f8d4110b069b}"/>
    <object class="SingleSound" id="{2261fe03-77a6-4d6e-ab79-865616aac57d}">
        <property name="pitch">
            <value>-1</value>
        </property>
        <relationship name="audioFile">
            <destination>{e08b48b2-5af0-4ca6-a145-6b873e1971dc}</destination>
        </relationship>
    </object>
    <object class="SingleSound" id="{ec0cc84a-3a05-45b9-98ce-1a0c967fb429}">
        <relationship name="audioFile">
            <destination>{2f2afcda-549e-42db-9059-3db33556f938}</destination>
        </relationship>
    </object>
    <object class="SingleSound" id="{7ca97bbe-23f8-4141-ba01-d0de388f328e}">
        <relationship name="audioFile">
            <destination>{730a6085-766d-4306-90c6-d2796da06095}</destination>
        </relationship>
    </object>
    <object class="MixerBusEffectChain" id="{5d252439-200f-461b-89f0-360635b470fb}">
        <relationship name="effects">
            <destination>{100b08b8-7034-41fd-b179-4abac6250f77}</destination>
        </relationship>
    </object>
    <object class="MixerBusPanner" id="{8d42dc06-b7f1-4c29-b059-fba4429723a2}"/>
    <object class="MixerBusFader" id="{4940ee67-826a-45df-8e5e-c160b2e86bd2}"/>
    <object class="MixerSend" id="{b6a5cd0a-d96e-4ad8-a66a-9d5de803f746}">
        <property name="inputFormat">
            <value>1</value>
        </property>
        <relationship name="mixerReturn">
            <destination>{12c215c2-057d-4f88-bd9f-2b906f6537c3}</destination>
        </relationship>
    </object>
    <object class="MixerBusFader" id="{100b08b8-7034-41fd-b179-4abac6250f77}"/>
</objects>
